{
    "https://github.com/cloudinary/cloudinary_npm": {
        "RampUp": 0.73,
        "License": 0,
        "Correctness": 0.67,
        "ResponsiveMaintainer": 0.68,
        "BusFactor": 0.62,
        "PR_Fraction": 0.63
    },
    "https://www.npmjs.com/package/express": {
        "License": 1,
        "Correctness": 0.95,
        "ResponsiveMaintainer": 0.85,
        "BusFactor": 0.58,
        "PR_Fraction": 0.83
    },
    "https://github.com/nullivex/nodist": {
        "License": 1,
        "Correctness": 0,
        "ResponsiveMaintainer": 0.34,
        "BusFactor": 0.72,
        "PR_Fraction": 0.8
    },
    "https://github.com/jonschlinkert/even": {
        "RampUp": 0.52,
        "License": 1,
        "Correctness": 1.0,
        "ResponsiveMaintainer": 0.5,
        "BusFactor": 0.88,
        "PR_Fraction": 0.0
    }
}